LICENSE
README.md
setup.py
grip4/__init__.py
grip4_connector.egg-info/PKG-INFO
grip4_connector.egg-info/SOURCES.txt
grip4_connector.egg-info/dependency_links.txt
grip4_connector.egg-info/requires.txt
grip4_connector.egg-info/top_level.txt