Metadata-Version: 2.1
Name: grip4-connector
Version: 0.0.3
Summary: GRIP4 Connector to get region road data from the Global Road Inventory Project
Home-page: https://github.com/Repsay/grip4-connector
Author: Jasper Delahaije
Author-email: jdelahaije@gmail.com
License: MIT
Download-URL: https://github.com/Repsay/grip4-connector/releases
Platform: UNKNOWN
Classifier: Development Status :: 2 - Pre-Alpha
Classifier: Intended Audience :: Developers
Classifier: Topic :: Software Development :: Libraries :: Python Modules
Classifier: Topic :: Utilities
Classifier: License :: OSI Approved :: MIT License
Classifier: Programming Language :: Python :: 3.8
Classifier: Programming Language :: Python :: 3.9
Classifier: Programming Language :: Python :: 3.10
Classifier: Natural Language :: English
Requires-Python: >=3.8
